pyconch/__init__.py
pyconch/configs.py
pyconch/main.py
pyconch/static.py
pyconch-0.0.5.dist-info/LICENSE
pyconch-0.0.5.dist-info/METADATA
pyconch-0.0.5.dist-info/WHEEL
pyconch-0.0.5.dist-info/entry_points.txt
pyconch-0.0.5.dist-info/top_level.txt
pyconch-0.0.5.dist-info/RECORD
