Metadata-Version: 2.1
Name: pyconch
Version: 0.0.5
Summary: Pyconch is a wrapper for a shell in python
Home-page: https://veltzer.github.io/pyconch
Download-URL: https://github.com/veltzer/pyconch
Author: Mark Veltzer
Author-email: mark.veltzer@gmail.com
Maintainer: Mark Veltzer
Maintainer-email: mark.veltzer@gmail.com
License: MIT
Keywords: shell,bash,tcsh
Platform: python3
Classifier: Development Status :: 4 - Beta
Classifier: Environment :: Console
Classifier: Operating System :: OS Independent
Classifier: Programming Language :: Python
Classifier: Programming Language :: Python :: 3
Classifier: Programming Language :: Python :: 3 :: Only
Classifier: Programming Language :: Python :: 3.11
Classifier: Topic :: Utilities
Classifier: License :: OSI Approved :: MIT License
License-File: LICENSE
Requires-Dist: pytconf
Requires-Dist: prompt-toolkit
Requires-Dist: ptterm
